impish/ImpishBroker.py
impish/ImpishClient.py
impish/__init__.py
impish/util/MessageType.py
impish/util/SocketMode.py
impish/util/__init__.py
impish/util/socket_util.py
impish-0.1.0.dist-info/METADATA
impish-0.1.0.dist-info/WHEEL
impish-0.1.0.dist-info/licenses/LICENSE
impish-0.1.0.dist-info/RECORD
