Metadata-Version: 2.1
Name: impish
Version: 0.1.0
Summary: A small package to simplify interprocess communication.
Project-URL: Homepage, https://github.com/CookieJ4R/impish
Project-URL: Bug Tracker, https://github.com/CookieJ4R/impish/issues
Author-email: Kevin Binder <cookiej4r.dev@gmail.com>
License-File: LICENSE
Classifier: License :: OSI Approved :: MIT License
Classifier: Operating System :: Microsoft :: Windows
Classifier: Operating System :: POSIX :: Linux
Classifier: Programming Language :: Python :: 3
Classifier: Topic :: Communications
Classifier: Topic :: Software Development :: Libraries
Classifier: Topic :: Software Development :: Object Brokering
Requires-Python: >=3.7
